{"node":{"type":"column","gap":1,"paddingX":1,"paddingY":0,"border":1,"text":"","children":[{"type":"row","gap":1,"paddingX":1,"paddingY":0,"border":0,"text":"","children":[{"type":"input","gap":0,"paddingX":1,"paddingY":0,"border":1,"text":"","children":[]},{"type":"button","gap":0,"paddingX":1,"paddingY":0,"border":1,"text":"Search","children":[]}]},{"type":"column","gap":1,"paddingX":1,"paddingY":0,"border":0,"text":"","children":[{"type":"row","gap":0,"paddingX":0,"paddingY":0,"border":0,"text":"","children":[{"type":"column","gap":0,"paddingX":0,"paddingY":0,"border":0,"text":"","children":[{"type":"text","gap":0,"paddingX":1,"paddingY":0,"border":1,"text":"HELLO WORLD","children":[]}]},{"type":"column","gap":0,"paddingX":0,"paddingY":0,"border":0,"text":"","children":[{"type":"text","gap":0,"paddingX":1,"paddingY":0,"border":1,"text":"HELLO WORLD","children":[]}]}]},{"type":"row","gap":0,"paddingX":0,"paddingY":0,"border":0,"text":"","children":[{"type":"column","gap":0,"paddingX":0,"paddingY":0,"border":0,"text":"","children":[{"type":"text","gap":0,"paddingX":1,"paddingY":0,"border":1,"text":"HELLO WORLD","children":[]}]},{"type":"column","gap":0,"paddingX":0,"paddingY":0,"border":0,"text":"","children":[{"type":"text","gap":0,"paddingX":1,"paddingY":0,"border":1,"text":"HELLO WORLD","children":[]}]}]}]},{"type":"row","gap":0,"paddingX":0,"paddingY":0,"border":1,"text":"","children":[{"type":"button","gap":0,"paddingX":1,"paddingY":0,"border":1,"text":"[P]prev","children":[]},{"type":"button","gap":0,"paddingX":1,"paddingY":0,"border":1,"text":"[N]ext","children":[]}]}]},"width":200,"height":49}